{
    "configurations": [
        {
            "name": "WSL Debian",
            "includePath": [
                "${workspaceFolder}/**",
                "${workspaceFolder}/bits_pointers_structs/kolmijako/include/**",
                "/usr/include/**",
                "/usr/local/include/**"
            ],
            "defines": [],
            "compilerPath": "/usr/bin/gcc",
            "cStandard": "c11",
            "cppStandard": "c++17",
            "intelliSenseMode": "linux-gcc-x64"
        }
    ],
    "version": 4
}
